MANIFEST.in
requirements.txt
setup.py
.venv/lib/python3.7/site-packages/numpy/f2py/src/fortranobject.c
.venv/lib/python3.7/site-packages/numpy/f2py/src/fortranobject.h
tests/__init__.py
valiml/__init__.py
valiml/classifiers.py
valiml/multiclass.py
valiml/optimizers.py
valiml.egg-info/PKG-INFO
valiml.egg-info/SOURCES.txt
valiml.egg-info/dependency_links.txt
valiml.egg-info/requires.txt
valiml.egg-info/top_level.txt
valiml.egg-info/zip-safe
valiml/boosting/AdaBoost.py
valiml/boosting/MulticlassDecisionStump.py
valiml/boosting/__init__.py
valiml/rl/__init__.py
valiml/rl/agents/AdversarialDQN.py
valiml/rl/agents/DQN.py
valiml/rl/agents/DoubleDQN.py
valiml/rl/agents/GreedyEpsilonPolicy.py
valiml/rl/agents/__init__.py
valiml/rl/agents/base.py
valiml/rl/algorithms/PrioritizedExperienceReplay.py
valiml/rl/algorithms/__init__.py
valiml/rl/memory/CircularMemory.py
valiml/rl/memory/PrioritizedMemory.py
valiml/rl/memory/__init__.py
valiml/rl/utils/RakingSampler.py
valiml/rl/utils/SumSegmentTree.py
valiml/rl/utils/Treaps.py
valiml/rl/utils/__init__.py
valiml/svm/HingeSVM.py
valiml/svm/__init__.py
valiml/utils/__init__.py
valiml/utils/numba_utils.py
valiml/utils/progbar.py
valiml/utils/utils.py
valiml/utils/src/__init__.py
valiml/utils/src/cffi.py
valiml/utils/src/utils.c
valiml/utils/src/utils.h