Metadata-Version: 1.1
Name: valiml
Version: 0.1.20
Summary: Extension of sklearn with tweaked implementation of common machine learning algorithms for self-use.
Home-page: UNKNOWN
Author: Valentin-Bogdan Rosca
Author-email: rosca.valentin2012@gmail.com
License: MIT
Platform: UNKNOWN
Classifier: Programming Language :: Python
Classifier: Programming Language :: Python :: 3.6
